conjuror/__init__.py
conjuror/cli.py
conjuror/dbm.py
conjuror/runcommands.py
conjuror/Auth/__init__.py
conjuror/Auth/djangoauth/__init__.py
conjuror/Auth/djangoauth/admin.py
conjuror/Auth/djangoauth/apps.py
conjuror/Auth/djangoauth/common.py
conjuror/Auth/djangoauth/models.py
conjuror/Auth/djangoauth/tests.py
conjuror/Auth/djangoauth/urls.py
conjuror/Auth/djangoauth/views.py
conjuror/Auth/djangoauth/email_templates/password_reset_email.html
conjuror/Auth/static/assets/css/bootstrap.css
conjuror/Auth/static/assets/css/bootstrap.min.css
conjuror/Auth/static/assets/css/font-awesome.min.css
conjuror/Auth/static/assets/css/index.css
conjuror/Auth/static/assets/css/owl.carousel.min.css
conjuror/Auth/static/assets/css/owl.theme.default.min.css
conjuror/Auth/static/assets/css/signup.css
conjuror/Auth/static/assets/css/style.css
conjuror/Auth/static/assets/fonts/FontAwesome.otf
conjuror/Auth/static/assets/fonts/et-line.eot
conjuror/Auth/static/assets/fonts/et-line.svg
conjuror/Auth/static/assets/fonts/et-line.ttf
conjuror/Auth/static/assets/fonts/et-line.woff
conjuror/Auth/static/assets/fonts/fontawesome-webfont.eot
conjuror/Auth/static/assets/fonts/fontawesome-webfont.svg
conjuror/Auth/static/assets/fonts/fontawesome-webfont.ttf
conjuror/Auth/static/assets/fonts/fontawesome-webfont.woff
conjuror/Auth/static/assets/fonts/fontawesome-webfont.woff2
conjuror/Auth/static/assets/fonts/icomoon.eot
conjuror/Auth/static/assets/fonts/icomoon.svg
conjuror/Auth/static/assets/fonts/icomoon.ttf
conjuror/Auth/static/assets/fonts/icomoon.woff
conjuror/Auth/static/assets/fonts/roboto-bold-webfont.eot
conjuror/Auth/static/assets/fonts/roboto-bold-webfont.svg
conjuror/Auth/static/assets/fonts/roboto-bold-webfont.ttf
conjuror/Auth/static/assets/fonts/roboto-bold-webfont.woff
conjuror/Auth/static/assets/fonts/roboto-bold-webfont.woff2
conjuror/Auth/static/assets/fonts/roboto-light-webfont.woff
conjuror/Auth/static/assets/fonts/roboto-light-webfont.woff2
DjangoConjuror-1.0.1.dist-info/License
DjangoConjuror-1.0.1.dist-info/METADATA
DjangoConjuror-1.0.1.dist-info/WHEEL
DjangoConjuror-1.0.1.dist-info/entry_points.txt
DjangoConjuror-1.0.1.dist-info/top_level.txt
DjangoConjuror-1.0.1.dist-info/RECORD
