Metadata-Version: 2.1
Name: DjangoConjuror
Version: 1.0.1
Summary: This tool is created to ease the Django Development. Developers can use this to create and manage their Django Projects.
Home-page: https://www.linkedin.com/in/hassan-farooq-65ba88280
Author: Hassan Farooq
Author-email: hassanfarooq0122@gmail.com
Classifier: Development Status :: 4 - Beta
Classifier: Environment :: Console
Classifier: Intended Audience :: Developers
Classifier: License :: OSI Approved :: MIT License
Classifier: Operating System :: OS Independent
Classifier: Programming Language :: Python :: 3
Classifier: Framework :: Django
License-File: License
Requires-Dist: django
Requires-Dist: requests
